AUTHORS.md
CONTRIBUTING.md
HISTORY.md
LICENSE
README.md
snyk_depxtractor/SnykClient.py
snyk_depxtractor/SnykConstants.py
snyk_depxtractor/__init__.py
snyk_depxtractor/cli.py
snyk_depxtractor/core.py
snyk_depxtractor-0.1.3.dist-info/entry_points.txt
snyk_depxtractor-0.1.3.dist-info/LICENSE
snyk_depxtractor-0.1.3.dist-info/WHEEL
snyk_depxtractor-0.1.3.dist-info/METADATA
snyk_depxtractor-0.1.3.dist-info/RECORD
