Metadata-Version: 2.1
Name: snyk-depxtractor
Version: 0.1.3
Summary: Snyk Dependency Extractor
Home-page: https://github.com/zsolt-halo/snyk-depxtractor
License: GPL-3.0-only
Author: Zsolt Halo
Author-email: net.zsolt.net@gmail.com
Requires-Python: >=3.10,<4.0
Classifier: Development Status :: 2 - Pre-Alpha
Classifier: Intended Audience :: Developers
Classifier: License :: OSI Approved :: GNU General Public License v3 (GPLv3)
Classifier: Natural Language :: English
Classifier: Programming Language :: Python :: 3
Classifier: Programming Language :: Python :: 3.10
Requires-Dist: click (>=8.0.3,<9.0.0)
Requires-Dist: pandas (>=1.3.5,<2.0.0)
Requires-Dist: pyarrow (>=6.0.1,<7.0.0)
Requires-Dist: requests (>=2.27.1,<3.0.0)
Requires-Dist: tqdm (>=4.62.3,<5.0.0)
Project-URL: Bug Tracker, https://github.com/zsolt-halo/snyk-depxtractor/issues
Project-URL: Repository, https://github.com/zsolt-halo/snyk-depxtractor
